[
	{
		"sourceSystem": {
			"code": "CRS",
			"name": "Naturalis - Zoology and Geology catalogues"
		},
		"sourceSystemId": "RMNH.5000004.a",
		"id": "RMNH.5000004.a@CRS",
		"unitID": "RMNH.5000004.a",
		"unitGUID": "http://data.biodiversitydata.nl/naturalis/specimen/RMNH.5000004.a",
		"sourceInstitutionID": "Naturalis Biodiversity Center",
		"sourceID": "CRS",
		"owner": "Naturalis Biodiversity Center",
		"licenseType": "Copyright",
		"license": "CC0",
		"recordBasis": "PreservedSpecimen",
		"kindOfUnit": "skin",
		"collectionType": "Aves",
		"sex": "male",
		"preparationType": "study skin",
		"numberOfSpecimen": 1,
		"fromCaptivity": false,
		"objectPublic": true,
		"multiMediaPublic": true,
		"gatheringEvent": {
			"country": "Al Maghrib",
			"locality": "Tagdilt",
			"localityText": "Morocco, Tagdilt",
			"dateTimeBegin": "2012-03-14T00:00:00+0000",
			"dateTimeEnd": "2012-03-14T00:00:00+0000",
			"gatheringPersons": [
				{
					"fullName": "Berg, A. van den"
				}
			],
			"siteCoordinates": [
				{
					"longitudeDecimal": -5.86,
					"latitudeDecimal": 31.25,
					"geoShape": {
						"type": "Point",
						"coordinates": [
							-5.86,
							31.25
						]
					}
				}
			]
		},
		"identifications": [
			{
				"taxonRank": "subspecies",
				"scientificName": {
					"fullScientificName": "Cursorius cursor cursor (Latham,1787)",
					"genusOrMonomial": "Cursorius",
					"specificEpithet": "cursor",
					"infraspecificEpithet": "cursor",
					"authorshipVerbatim": "Latham,1787",
					"scientificNameGroup": "cursorius cursor cursor"
				},
				"defaultClassification": {
					"family": "Glareolidae",
					"genus": "Cursorius",
					"specificEpithet": "cursor",
					"infraspecificEpithet": "cursor"
				},
				"preferred": true
			}
		]
	}
]